LABB/up.v
module Lab_Test6_Up(output A2,A1,A0,input CLK, Reset);
    
Comp_D_flip_flop F0 (A0, CLK, Reset);
Comp_D_flip_flop F1 (A1, A0, Reset);
Comp_D_flip_flop F2 (A2, A1, Reset);

endmodule


module Lab_Test6_Down(output A2,A1,A0,input CLK, Reset);
    
     Comp_D_flip_flop F0 (A0, ~CLK, Reset);
   Comp_D_flip_flop F1 (A1, ~A0, Reset);
   Comp_D_flip_flop F2 (A2, ~A1, Reset);

endmodule

module Comp_D_flip_flop (Q, CLK, Reset);
   output Q;
   input CLK, Reset;
   reg Q;
   always @ ( negedge CLK, posedge Reset)
   if (Reset) 
     Q <= 1'b0;
   else
  
     Q <=  ~Q;
endmodule

module t_Lab_Test6;
   reg CLK;
  reg Reset;
  wire [2:0] A;
  wire [2:0] B;
  
   Lab_Test6_Up N (A[2], A[1], A[0], CLK, Reset);
   Lab_Test6_Down P (B[2], B[1], B[0], CLK, Reset);  
  
  initial 
    begin
      $dumpfile("t_Lab_Test6.vcd");
      $dumpvars(0, t_Lab_Test6);
    end 
   initial #170 $finish;   
     initial
       begin
         CLK = 1'b0;
         repeat(33)
           #5 CLK = ~CLK; 
        end
  initial
   begin
     #4 Reset = 1'b0;
    #4 Reset = 1'b1;
        #4 Reset = 1'b0; 
   end
endmodule

LABB/t_Lab_Test6.vcd
$date
	Wed Nov 20 02:31:31 2024
$end
$version
	Icarus Verilog
$end
$timescale
	1s
$end
$scope module t_Lab_Test6 $end
$var wire 3 ! B [2:0] $end
$var wire 3 " A [2:0] $end
$var reg 1 # CLK $end
$var reg 1 $ Reset $end
$scope module N $end
$var wire 1 # CLK $end
$var wire 1 $ Reset $end
$var wire 1 % A2 $end
$var wire 1 & A1 $end
$var wire 1 ' A0 $end
$scope module F0 $end
$var wire 1 # CLK $end
$var wire 1 $ Reset $end
$var reg 1 ' Q $end
$upscope $end
$scope module F1 $end
$var wire 1 ' CLK $end
$var wire 1 $ Reset $end
$var reg 1 & Q $end
$upscope $end
$scope module F2 $end
$var wire 1 & CLK $end
$var wire 1 $ Reset $end
$var reg 1 % Q $end
$upscope $end
$upscope $end
$scope module P $end
$var wire 1 # CLK $end
$var wire 1 $ Reset $end
$var wire 1 ( A2 $end
$var wire 1 ) A1 $end
$var wire 1 * A0 $end
$scope module F0 $end
$var wire 1 + CLK $end
$var wire 1 $ Reset $end
$var reg 1 * Q $end
$upscope $end
$scope module F1 $end
$var wire 1 , CLK $end
$var wire 1 $ Reset $end
$var reg 1 ) Q $end
$upscope $end
$scope module F2 $end
$var wire 1 - CLK $end
$var wire 1 $ Reset $end
$var reg 1 ( Q $end
$upscope $end
$upscope $end
$upscope $end
$enddefinitions $end
$comment Show the parameter values. $end
$dumpall
$end
#0
$dumpvars
x-
x,
1+
x*
x)
x(
x'
x&
x%
x$
0#
bx "
bx !
$end
#4
0$
#5
0+
1#
#8
1,
1-
0'
0&
b0 "
0%
0*
0)
b0 !
0(
1$
#10
1+
0#
#12
0$
#15
1(
0-
1)
0,
b111 !
1*
0+
1#
#20
b1 "
1'
1+
0#
#25
1,
b110 !
0*
0+
1#
#30
1&
b10 "
0'
1+
0#
#35
1-
0)
0,
b101 !
1*
0+
1#
#40
b11 "
1'
1+
0#
#45
1,
b100 !
0*
0+
1#
#50
1%
0&
b100 "
0'
1+
0#
#55
0(
0-
1)
0,
b11 !
1*
0+
1#
#60
b101 "
1'
1+
0#
#65
1,
b10 !
0*
0+
1#
#70
1&
b110 "
0'
1+
0#
#75
1-
0)
0,
b1 !
1*
0+
1#
#80
b111 "
1'
1+
0#
#85
1,
b0 !
0*
0+
1#
#90
0%
0&
b0 "
0'
1+
0#
#95
1(
0-
1)
0,
b111 !
1*
0+
1#
#100
b1 "
1'
1+
0#
#105
1,
b110 !
0*
0+
1#
#110
1&
b10 "
0'
1+
0#
#115
1-
0)
0,
b101 !
1*
0+
1#
#120
b11 "
1'
1+
0#
#125
1,
b100 !
0*
0+
1#
#130
1%
0&
b100 "
0'
1+
0#
#135
0(
0-
1)
0,
b11 !
1*
0+
1#
#140
b101 "
1'
1+
0#
#145
1,
b10 !
0*
0+
1#
#150
1&
b110 "
0'
1+
0#
#155
1-
0)
0,
b1 !
1*
0+
1#
#160
b111 "
1'
1+
0#
#165
1,
b0 !
0*
0+
1#
