DSA/LinkedList/230211_Sakib.v
module NAND(
    output FNAND,
    input w, x, y, z);
    wire w_inv, x_inv, y_inv, z_inv, temp1, temp2, temp3;
    
    nand G1(w_inv, w, w); 
    nand G2(x_inv, x, x);  
    nand G3(y_inv, y, y);  
    nand G4(z_inv, z, z);  
    nand G5(temp1, w, x_inv);  
    nand G6(temp2, y_inv, z_inv); 
    nand G7(temp3, w_inv, z_inv); 
    
    nand G8(FNAND, temp1, temp2, temp3);  
endmodule

module NOR(
    output FNOR,
    input w, x, y, z);
    wire w_inv, x_inv, y_inv, z_inv, temp1, temp2, temp3;
    
    nor G1(w_inv, w, w);  
    nor G2(x_inv, x, x);  
    nor G3(y_inv, y, y);  
    nor G4(z_inv, z, z);  
    nor G5(temp1, w, z_inv);  
    nor G6(temp2, x_inv, z_inv); 
    nor G7(temp3, w_inv, x_inv, y_inv); 
    
    nor G8(FNOR, temp1, temp2, temp3);
endmodule

module Sakib;
    wire FNOR, FNAND;
    reg w, x, y, z;

    NOR nr(FNOR, w, x, y, z);
    NAND np(FNAND, w, x, y, z);

    initial begin
        $dumpfile("Sakib.vcd");
        $dumpvars(0, Sakib);

            w = 1'b0; x = 1'b0; y = 1'b0; z = 1'b0;
        #10 w = 1'b0; x = 1'b0; y = 1'b0; z = 1'b1;
        #10 w = 1'b0; x = 1'b0; y = 1'b1; z = 1'b0;
        #10 w = 1'b0; x = 1'b0; y = 1'b1; z = 1'b1;
        #10 w = 1'b0; x = 1'b1; y = 1'b0; z = 1'b0;
        #10 w = 1'b0; x = 1'b1; y = 1'b0; z = 1'b1;
        #10 w = 1'b0; x = 1'b1; y = 1'b1; z = 1'b0;
        #10 w = 1'b0; x = 1'b1; y = 1'b1; z = 1'b1;
        #10 w = 1'b1; x = 1'b0; y = 1'b0; z = 1'b0;
        #10 w = 1'b1; x = 1'b0; y = 1'b0; z = 1'b1;
        #10 w = 1'b1; x = 1'b0; y = 1'b1; z = 1'b0;
        #10 w = 1'b1; x = 1'b0; y = 1'b1; z = 1'b1;
        #10 w = 1'b1; x = 1'b1; y = 1'b0; z = 1'b0;
        #10 w = 1'b1; x = 1'b1; y = 1'b0; z = 1'b1;
        #10 w = 1'b1; x = 1'b1; y = 1'b1; z = 1'b0;
        #10 w = 1'b1; x = 1'b1; y = 1'b1; z = 1'b1;
    end

    initial #160 $finish;
endmodule

DSA/LinkedList/Sakib.vcd
$date
	Sun Sep 22 09:59:07 2024
$end
$version
	Icarus Verilog
$end
$timescale
	1s
$end
$scope module Sakib $end
$var wire 1 ! FNOR $end
$var wire 1 " FNAND $end
$var reg 1 # w $end
$var reg 1 $ x $end
$var reg 1 % y $end
$var reg 1 & z $end
$scope module np $end
$var wire 1 " FNAND $end
$var wire 1 ' temp1 $end
$var wire 1 ( temp2 $end
$var wire 1 ) temp3 $end
$var wire 1 # w $end
$var wire 1 * w_inv $end
$var wire 1 $ x $end
$var wire 1 + x_inv $end
$var wire 1 % y $end
$var wire 1 , y_inv $end
$var wire 1 & z $end
$var wire 1 - z_inv $end
$upscope $end
$scope module nr $end
$var wire 1 ! FNOR $end
$var wire 1 . temp1 $end
$var wire 1 / temp2 $end
$var wire 1 0 temp3 $end
$var wire 1 # w $end
$var wire 1 1 w_inv $end
$var wire 1 $ x $end
$var wire 1 2 x_inv $end
$var wire 1 % y $end
$var wire 1 3 y_inv $end
$var wire 1 & z $end
$var wire 1 4 z_inv $end
$upscope $end
$upscope $end
$enddefinitions $end
$comment Show the parameter values. $end
$dumpall
$end
#0
$dumpvars
14
13
12
11
00
0/
0.
1-
1,
1+
1*
0)
0(
1'
0&
0%
0$
0#
1"
1!
$end
#10
0"
0!
1(
1)
1.
0-
04
1&
#20
1"
1!
0)
0.
1-
14
0,
03
0&
1%
#30
0"
0!
1)
1.
0-
04
1&
#40
1!
1"
0)
0.
0(
1-
14
1,
13
0+
02
0&
0%
1$
#50
0"
0!
1(
1)
1.
1/
0-
04
1&
#60
1"
1!
0)
0.
0/
1-
14
0,
03
0&
1%
#70
0"
0!
1)
1.
1/
0-
04
1&
#80
1"
1!
0(
0'
0/
1-
14
1,
13
1+
12
0*
01
0.
0&
0%
0$
1#
#90
1(
0-
04
1&
#100
1-
14
0,
03
0&
1%
#110
0-
04
1&
#120
0(
1'
1-
14
1,
13
0+
02
0&
0%
1$
#130
0"
0!
1(
1/
0-
04
1&
#140
0/
10
1-
14
0,
03
0&
1%
#150
1/
0-
04
1&
